llama_index/retrievers/bm25/__init__.py
llama_index/retrievers/bm25/base.py
llama_index_retrievers_bm25-0.6.5.dist-info/METADATA
llama_index_retrievers_bm25-0.6.5.dist-info/WHEEL
llama_index_retrievers_bm25-0.6.5.dist-info/licenses/LICENSE
llama_index_retrievers_bm25-0.6.5.dist-info/RECORD
